Candy_reply/__init__.py
Candy_reply/utils.py
Candy_reply-1.0.2.dist-info/LICENSE
Candy_reply-1.0.2.dist-info/METADATA
Candy_reply-1.0.2.dist-info/WHEEL
Candy_reply-1.0.2.dist-info/top_level.txt
Candy_reply-1.0.2.dist-info/RECORD
